{
  "vtex.menu@2.x:menu#category-menu": {
    "props": {
      "experimentalOptimizeRendering": true
    },
    "children": [
      "menu-item#category-apparel"
    ]
  },
  "menu-item#category-apparel": {
    "props": {
      "id": "menu-item-category-apparel",
      "type": "custom",
      "iconId": null,
      "highlight": false,
      "itemProps": {
        "type": "internal",
        "href": "/apparel---accessories/",
        "noFollow": false,
        "tagTitle": "Apparel & Accessories",
        "text": "Apparel & Accessories"
      }
    },
    "blocks": [
      "vtex.menu@2.x:submenu#category-apparel"
    ]
  },
  "vtex.menu@2.x:submenu#category-apparel": {
    "props": {
      "width": "auto"
    },
    "children": [
      "vtex.menu@2.x:menu#category-apparel"
    ]
  },
  "vtex.menu@2.x:menu#category-apparel": {
    "props": {
      "orientation": "vertical"
    },
    "children": [
      "menu-item#category-apparel-clothing",
      "menu-item#category-apparel-accessories",
      "menu-item#category-apparel-eyeglasses"
    ]
  },
  "menu-item#category-apparel-clothing": {
    "props": {
      "id": "menu-item-category-apparel-clothing",
      "type": "custom",
      "iconId": null,
      "highlight": false,
      "itemProps": {
        "type": "internal",
        "href": "/apparel---accessories/clothing/",
        "noFollow": false,
        "tagTitle": "Clothing",
        "text": "Clothing"
      }
    }
  },
  "menu-item#category-apparel-accessories": {
    "props": {
      "id": "menu-item-category-apparel-accessories",
      "type": "custom",
      "iconId": null,
      "highlight": false,
      "itemProps": {
        "type": "internal",
        "href": "/apparel---accessories/accessories/",
        "noFollow": false,
        "tagTitle": "Accessories",
        "text": "Accessories"
      }
    }
  },
  "menu-item#category-apparel-eyeglasses": {
    "props": {
      "id": "menu-item-category-apparel-eyeglasses",
      "type": "custom",
      "iconId": null,
      "highlight": false,
      "itemProps": {
        "type": "internal",
        "href": "/apparel---accessories/eyeglasses/",
        "noFollow": false,
        "tagTitle": "Eyeglasses",
        "text": "Eyeglasses"
      }
    }
  }
}